ideariver_services/__init__.py
ideariver_services/plugin_loader.py
ideariver_services/plugin_rabbitmq_adapter.py
ideariver_services/plugin_tester.py
ideariver_services/validate_inputs.py
ideariver_services-0.1.2.dist-info/LICENSE
ideariver_services-0.1.2.dist-info/METADATA
ideariver_services-0.1.2.dist-info/WHEEL
ideariver_services-0.1.2.dist-info/top_level.txt
ideariver_services-0.1.2.dist-info/RECORD
