Metadata-Version: 2.1
Name: ideariver-services
Version: 0.1.2
Summary: A collection of services used by the ideariver ecosystem.
Author: Your Name
Author-email: youremail@example.com
Classifier: Programming Language :: Python :: 3
Classifier: License :: OSI Approved :: MIT License
Classifier: Operating System :: OS Independent
Requires-Python: >=3.6
License-File: LICENSE
